{
    "profiles": [
        {
            "devices": [
                {
                    "identifiers": { "is_keyboard": true },
                    "ignore": true
                },
                {
                    "disable_built_in_keyboard_if_exists": true,
                    "identifiers": {
                        "is_keyboard": true,
                        "is_pointing_device": true,
                        "product_id": 560,
                        "vendor_id": 13364
                    },
                    "ignore": false
                },
                {
                    "identifiers": {
                        "is_keyboard": true,
                        "is_pointing_device": true,
                        "product_id": 26145,
                        "vendor_id": 12994
                    },
                    "ignore": false,
                    "manipulate_caps_lock_led": false,
                    "mouse_flip_vertical_wheel": true
                }
            ],
            "name": "Default profile",
            "selected": true,
            "virtual_hid_keyboard": {
                "country_code": 0,
                "keyboard_type_v2": "ansi"
            }
        }
    ]
}